{
	"configurations" : 
	[
		{
			"directories" : 
			[
				{
					"build" : ".",
					"childIndexes" : 
					[
						1,
						6,
						8
					],
					"hasInstallRule" : true,
					"jsonFile" : "directory-.-Debug-d0094a50bb2071803777.json",
					"minimumCMakeVersion" : 
					{
						"string" : "3.30"
					},
					"projectIndex" : 0,
					"source" : ".",
					"targetIndexes" : 
					[
						0,
						8,
						12
					]
				},
				{
					"build" : "ExternalProjects",
					"childIndexes" : 
					[
						2,
						5
					],
					"hasInstallRule" : true,
					"jsonFile" : "directory-ExternalProjects-Debug-922e8866d1c48627fdd8.json",
					"minimumCMakeVersion" : 
					{
						"string" : "3.30"
					},
					"parentIndex" : 0,
					"projectIndex" : 0,
					"source" : "ExternalProjects",
					"targetIndexes" : 
					[
						5
					]
				},
				{
					"build" : "ExternalProjects/glfw",
					"childIndexes" : 
					[
						3,
						4
					],
					"hasInstallRule" : true,
					"jsonFile" : "directory-ExternalProjects.glfw-Debug-ea1df67d390e019927b6.json",
					"minimumCMakeVersion" : 
					{
						"string" : "3.16"
					},
					"parentIndex" : 1,
					"projectIndex" : 1,
					"source" : "ExternalProjects/glfw",
					"targetIndexes" : 
					[
						1,
						15
					]
				},
				{
					"build" : "ExternalProjects/glfw/src",
					"hasInstallRule" : true,
					"jsonFile" : "directory-ExternalProjects.glfw.src-Debug-82f4b0917742b834a6fa.json",
					"minimumCMakeVersion" : 
					{
						"string" : "3.16"
					},
					"parentIndex" : 2,
					"projectIndex" : 1,
					"source" : "ExternalProjects/glfw/src",
					"targetIndexes" : 
					[
						13,
						16
					]
				},
				{
					"build" : "ExternalProjects/glfw/docs",
					"jsonFile" : "directory-ExternalProjects.glfw.docs-Debug-532e040bf42a7d32092a.json",
					"minimumCMakeVersion" : 
					{
						"string" : "3.16"
					},
					"parentIndex" : 2,
					"projectIndex" : 1,
					"source" : "ExternalProjects/glfw/docs"
				},
				{
					"build" : "ExternalProjects/tinyobjloader",
					"hasInstallRule" : true,
					"jsonFile" : "directory-ExternalProjects.tinyobjloader-Debug-0337663cd3d97582dc6c.json",
					"minimumCMakeVersion" : 
					{
						"string" : "3.16"
					},
					"parentIndex" : 1,
					"projectIndex" : 2,
					"source" : "ExternalProjects/tinyobjloader",
					"targetIndexes" : 
					[
						2,
						14
					]
				},
				{
					"build" : "SupportProjects",
					"childIndexes" : 
					[
						7
					],
					"jsonFile" : "directory-SupportProjects-Debug-4b0124a991b4f3aaa621.json",
					"minimumCMakeVersion" : 
					{
						"string" : "3.30"
					},
					"parentIndex" : 0,
					"projectIndex" : 0,
					"source" : "SupportProjects",
					"targetIndexes" : 
					[
						9
					]
				},
				{
					"build" : "SupportProjects/NeftyRenderTools",
					"jsonFile" : "directory-SupportProjects.NeftyRenderTools-Debug-a11cc44d347d24b5317d.json",
					"minimumCMakeVersion" : 
					{
						"string" : "3.30"
					},
					"parentIndex" : 6,
					"projectIndex" : 3,
					"source" : "SupportProjects/NeftyRenderTools",
					"targetIndexes" : 
					[
						3,
						6,
						7
					]
				},
				{
					"build" : "MainProject",
					"childIndexes" : 
					[
						9
					],
					"jsonFile" : "directory-MainProject-Debug-01b36ebcf08f83310bad.json",
					"minimumCMakeVersion" : 
					{
						"string" : "3.30.0"
					},
					"parentIndex" : 0,
					"projectIndex" : 4,
					"source" : "MainProject",
					"targetIndexes" : 
					[
						4
					]
				},
				{
					"build" : "MainProject/Product",
					"jsonFile" : "directory-MainProject.Product-Debug-6430a5e855460a19d6c4.json",
					"minimumCMakeVersion" : 
					{
						"string" : "3.30.0"
					},
					"parentIndex" : 8,
					"projectIndex" : 4,
					"source" : "MainProject/Product",
					"targetIndexes" : 
					[
						10,
						11
					]
				}
			],
			"name" : "Debug",
			"projects" : 
			[
				{
					"childIndexes" : 
					[
						1,
						2,
						3,
						4
					],
					"directoryIndexes" : 
					[
						0,
						1,
						6
					],
					"name" : "RayStudioPhase_1",
					"targetIndexes" : 
					[
						0,
						5,
						8,
						9,
						12
					]
				},
				{
					"directoryIndexes" : 
					[
						2,
						3,
						4
					],
					"name" : "GLFW",
					"parentIndex" : 0,
					"targetIndexes" : 
					[
						1,
						13,
						15,
						16
					]
				},
				{
					"directoryIndexes" : 
					[
						5
					],
					"name" : "tinyobjloader",
					"parentIndex" : 0,
					"targetIndexes" : 
					[
						2,
						14
					]
				},
				{
					"directoryIndexes" : 
					[
						7
					],
					"name" : "SupporterNeftyRenderTools",
					"parentIndex" : 0,
					"targetIndexes" : 
					[
						3,
						6,
						7
					]
				},
				{
					"directoryIndexes" : 
					[
						8,
						9
					],
					"name" : "Seohyuk",
					"parentIndex" : 0,
					"targetIndexes" : 
					[
						4,
						10,
						11
					]
				}
			],
			"targets" : 
			[
				{
					"directoryIndex" : 0,
					"id" : "ALL_BUILD::@6890427a1f51a3e7e1df",
					"jsonFile" : "target-ALL_BUILD-Debug-d2bce6edf4d055655a1d.json",
					"name" : "ALL_BUILD",
					"projectIndex" : 0
				},
				{
					"directoryIndex" : 2,
					"id" : "ALL_BUILD::@bbdae231e67c99e26acc",
					"jsonFile" : "target-ALL_BUILD-Debug-ff9bfa6a58bd85a00813.json",
					"name" : "ALL_BUILD",
					"projectIndex" : 1
				},
				{
					"directoryIndex" : 5,
					"id" : "ALL_BUILD::@f5b758276623e14bdd9d",
					"jsonFile" : "target-ALL_BUILD-Debug-0d2c9e557ee6952a99e1.json",
					"name" : "ALL_BUILD",
					"projectIndex" : 2
				},
				{
					"directoryIndex" : 7,
					"id" : "ALL_BUILD::@ce0a2fa435a966c906ac",
					"jsonFile" : "target-ALL_BUILD-Debug-2b4cc54be70e18fa6d87.json",
					"name" : "ALL_BUILD",
					"projectIndex" : 3
				},
				{
					"directoryIndex" : 8,
					"id" : "ALL_BUILD::@04e0e633e5cbf44b3816",
					"jsonFile" : "target-ALL_BUILD-Debug-64e0b1cdc76b906d332f.json",
					"name" : "ALL_BUILD",
					"projectIndex" : 4
				},
				{
					"directoryIndex" : 1,
					"id" : "EXTERNAL_OBJECTS::@1687bc44cdbe44ae90e7",
					"jsonFile" : "target-EXTERNAL_OBJECTS-Debug-183ce34d7669996c6a5d.json",
					"name" : "EXTERNAL_OBJECTS",
					"projectIndex" : 0
				},
				{
					"directoryIndex" : 7,
					"id" : "NeftyRenderTools::@ce0a2fa435a966c906ac",
					"jsonFile" : "target-NeftyRenderTools-Debug-f04c07de0d4c418a9c02.json",
					"name" : "NeftyRenderTools",
					"projectIndex" : 3
				},
				{
					"directoryIndex" : 7,
					"id" : "NeftyRenderToolsTest::@ce0a2fa435a966c906ac",
					"jsonFile" : "target-NeftyRenderToolsTest-Debug-975d7a9d5d18031e6585.json",
					"name" : "NeftyRenderToolsTest",
					"projectIndex" : 3
				},
				{
					"directoryIndex" : 0,
					"id" : "SETUPS::@6890427a1f51a3e7e1df",
					"jsonFile" : "target-SETUPS-Debug-60f6e4d21ed9a32c1a20.json",
					"name" : "SETUPS",
					"projectIndex" : 0
				},
				{
					"directoryIndex" : 6,
					"id" : "SUPPORT_OBJECTS::@eb26578ef4342958058a",
					"jsonFile" : "target-SUPPORT_OBJECTS-Debug-920badb61cd04942a524.json",
					"name" : "SUPPORT_OBJECTS",
					"projectIndex" : 0
				},
				{
					"directoryIndex" : 9,
					"id" : "TeapotBasic::@e35cb58959e57316dddd",
					"jsonFile" : "target-TeapotBasic-Debug-9067794f21d5dde97e48.json",
					"name" : "TeapotBasic",
					"projectIndex" : 4
				},
				{
					"directoryIndex" : 9,
					"id" : "Triangle::@e35cb58959e57316dddd",
					"jsonFile" : "target-Triangle-Debug-63b14ca9a636858dc4fa.json",
					"name" : "Triangle",
					"projectIndex" : 4
				},
				{
					"directoryIndex" : 0,
					"id" : "ZERO_CHECK::@6890427a1f51a3e7e1df",
					"jsonFile" : "target-ZERO_CHECK-Debug-251a86dddb8cffc32e6c.json",
					"name" : "ZERO_CHECK",
					"projectIndex" : 0
				},
				{
					"directoryIndex" : 3,
					"id" : "glfw::@82b6fd495907bb2a0cc8",
					"jsonFile" : "target-glfw-Debug-d8c197be46b2890b9531.json",
					"name" : "glfw",
					"projectIndex" : 1
				},
				{
					"directoryIndex" : 5,
					"id" : "tinyobjloader::@f5b758276623e14bdd9d",
					"jsonFile" : "target-tinyobjloader-Debug-002b2d9b7d7bf982052b.json",
					"name" : "tinyobjloader",
					"projectIndex" : 2
				},
				{
					"directoryIndex" : 2,
					"id" : "uninstall::@bbdae231e67c99e26acc",
					"jsonFile" : "target-uninstall-Debug-5c6bd9945a3443d87f85.json",
					"name" : "uninstall",
					"projectIndex" : 1
				},
				{
					"directoryIndex" : 3,
					"id" : "update_mappings::@82b6fd495907bb2a0cc8",
					"jsonFile" : "target-update_mappings-Debug-ff72683483d2b26869b9.json",
					"name" : "update_mappings",
					"projectIndex" : 1
				}
			]
		},
		{
			"directories" : 
			[
				{
					"build" : ".",
					"childIndexes" : 
					[
						1,
						6,
						8
					],
					"hasInstallRule" : true,
					"jsonFile" : "directory-.-Release-d0094a50bb2071803777.json",
					"minimumCMakeVersion" : 
					{
						"string" : "3.30"
					},
					"projectIndex" : 0,
					"source" : ".",
					"targetIndexes" : 
					[
						0,
						8,
						12
					]
				},
				{
					"build" : "ExternalProjects",
					"childIndexes" : 
					[
						2,
						5
					],
					"hasInstallRule" : true,
					"jsonFile" : "directory-ExternalProjects-Release-922e8866d1c48627fdd8.json",
					"minimumCMakeVersion" : 
					{
						"string" : "3.30"
					},
					"parentIndex" : 0,
					"projectIndex" : 0,
					"source" : "ExternalProjects",
					"targetIndexes" : 
					[
						5
					]
				},
				{
					"build" : "ExternalProjects/glfw",
					"childIndexes" : 
					[
						3,
						4
					],
					"hasInstallRule" : true,
					"jsonFile" : "directory-ExternalProjects.glfw-Release-ea1df67d390e019927b6.json",
					"minimumCMakeVersion" : 
					{
						"string" : "3.16"
					},
					"parentIndex" : 1,
					"projectIndex" : 1,
					"source" : "ExternalProjects/glfw",
					"targetIndexes" : 
					[
						1,
						15
					]
				},
				{
					"build" : "ExternalProjects/glfw/src",
					"hasInstallRule" : true,
					"jsonFile" : "directory-ExternalProjects.glfw.src-Release-cd42be1c805e5cc040bb.json",
					"minimumCMakeVersion" : 
					{
						"string" : "3.16"
					},
					"parentIndex" : 2,
					"projectIndex" : 1,
					"source" : "ExternalProjects/glfw/src",
					"targetIndexes" : 
					[
						13,
						16
					]
				},
				{
					"build" : "ExternalProjects/glfw/docs",
					"jsonFile" : "directory-ExternalProjects.glfw.docs-Release-532e040bf42a7d32092a.json",
					"minimumCMakeVersion" : 
					{
						"string" : "3.16"
					},
					"parentIndex" : 2,
					"projectIndex" : 1,
					"source" : "ExternalProjects/glfw/docs"
				},
				{
					"build" : "ExternalProjects/tinyobjloader",
					"hasInstallRule" : true,
					"jsonFile" : "directory-ExternalProjects.tinyobjloader-Release-418256cb722f98a45fb9.json",
					"minimumCMakeVersion" : 
					{
						"string" : "3.16"
					},
					"parentIndex" : 1,
					"projectIndex" : 2,
					"source" : "ExternalProjects/tinyobjloader",
					"targetIndexes" : 
					[
						2,
						14
					]
				},
				{
					"build" : "SupportProjects",
					"childIndexes" : 
					[
						7
					],
					"jsonFile" : "directory-SupportProjects-Release-4b0124a991b4f3aaa621.json",
					"minimumCMakeVersion" : 
					{
						"string" : "3.30"
					},
					"parentIndex" : 0,
					"projectIndex" : 0,
					"source" : "SupportProjects",
					"targetIndexes" : 
					[
						9
					]
				},
				{
					"build" : "SupportProjects/NeftyRenderTools",
					"jsonFile" : "directory-SupportProjects.NeftyRenderTools-Release-a11cc44d347d24b5317d.json",
					"minimumCMakeVersion" : 
					{
						"string" : "3.30"
					},
					"parentIndex" : 6,
					"projectIndex" : 3,
					"source" : "SupportProjects/NeftyRenderTools",
					"targetIndexes" : 
					[
						3,
						6,
						7
					]
				},
				{
					"build" : "MainProject",
					"childIndexes" : 
					[
						9
					],
					"jsonFile" : "directory-MainProject-Release-01b36ebcf08f83310bad.json",
					"minimumCMakeVersion" : 
					{
						"string" : "3.30.0"
					},
					"parentIndex" : 0,
					"projectIndex" : 4,
					"source" : "MainProject",
					"targetIndexes" : 
					[
						4
					]
				},
				{
					"build" : "MainProject/Product",
					"jsonFile" : "directory-MainProject.Product-Release-6430a5e855460a19d6c4.json",
					"minimumCMakeVersion" : 
					{
						"string" : "3.30.0"
					},
					"parentIndex" : 8,
					"projectIndex" : 4,
					"source" : "MainProject/Product",
					"targetIndexes" : 
					[
						10,
						11
					]
				}
			],
			"name" : "Release",
			"projects" : 
			[
				{
					"childIndexes" : 
					[
						1,
						2,
						3,
						4
					],
					"directoryIndexes" : 
					[
						0,
						1,
						6
					],
					"name" : "RayStudioPhase_1",
					"targetIndexes" : 
					[
						0,
						5,
						8,
						9,
						12
					]
				},
				{
					"directoryIndexes" : 
					[
						2,
						3,
						4
					],
					"name" : "GLFW",
					"parentIndex" : 0,
					"targetIndexes" : 
					[
						1,
						13,
						15,
						16
					]
				},
				{
					"directoryIndexes" : 
					[
						5
					],
					"name" : "tinyobjloader",
					"parentIndex" : 0,
					"targetIndexes" : 
					[
						2,
						14
					]
				},
				{
					"directoryIndexes" : 
					[
						7
					],
					"name" : "SupporterNeftyRenderTools",
					"parentIndex" : 0,
					"targetIndexes" : 
					[
						3,
						6,
						7
					]
				},
				{
					"directoryIndexes" : 
					[
						8,
						9
					],
					"name" : "Seohyuk",
					"parentIndex" : 0,
					"targetIndexes" : 
					[
						4,
						10,
						11
					]
				}
			],
			"targets" : 
			[
				{
					"directoryIndex" : 0,
					"id" : "ALL_BUILD::@6890427a1f51a3e7e1df",
					"jsonFile" : "target-ALL_BUILD-Release-d2bce6edf4d055655a1d.json",
					"name" : "ALL_BUILD",
					"projectIndex" : 0
				},
				{
					"directoryIndex" : 2,
					"id" : "ALL_BUILD::@bbdae231e67c99e26acc",
					"jsonFile" : "target-ALL_BUILD-Release-ff9bfa6a58bd85a00813.json",
					"name" : "ALL_BUILD",
					"projectIndex" : 1
				},
				{
					"directoryIndex" : 5,
					"id" : "ALL_BUILD::@f5b758276623e14bdd9d",
					"jsonFile" : "target-ALL_BUILD-Release-0d2c9e557ee6952a99e1.json",
					"name" : "ALL_BUILD",
					"projectIndex" : 2
				},
				{
					"directoryIndex" : 7,
					"id" : "ALL_BUILD::@ce0a2fa435a966c906ac",
					"jsonFile" : "target-ALL_BUILD-Release-2b4cc54be70e18fa6d87.json",
					"name" : "ALL_BUILD",
					"projectIndex" : 3
				},
				{
					"directoryIndex" : 8,
					"id" : "ALL_BUILD::@04e0e633e5cbf44b3816",
					"jsonFile" : "target-ALL_BUILD-Release-64e0b1cdc76b906d332f.json",
					"name" : "ALL_BUILD",
					"projectIndex" : 4
				},
				{
					"directoryIndex" : 1,
					"id" : "EXTERNAL_OBJECTS::@1687bc44cdbe44ae90e7",
					"jsonFile" : "target-EXTERNAL_OBJECTS-Release-183ce34d7669996c6a5d.json",
					"name" : "EXTERNAL_OBJECTS",
					"projectIndex" : 0
				},
				{
					"directoryIndex" : 7,
					"id" : "NeftyRenderTools::@ce0a2fa435a966c906ac",
					"jsonFile" : "target-NeftyRenderTools-Release-dfc5325af49384b8deb3.json",
					"name" : "NeftyRenderTools",
					"projectIndex" : 3
				},
				{
					"directoryIndex" : 7,
					"id" : "NeftyRenderToolsTest::@ce0a2fa435a966c906ac",
					"jsonFile" : "target-NeftyRenderToolsTest-Release-b69078ca35d632e5c657.json",
					"name" : "NeftyRenderToolsTest",
					"projectIndex" : 3
				},
				{
					"directoryIndex" : 0,
					"id" : "SETUPS::@6890427a1f51a3e7e1df",
					"jsonFile" : "target-SETUPS-Release-60f6e4d21ed9a32c1a20.json",
					"name" : "SETUPS",
					"projectIndex" : 0
				},
				{
					"directoryIndex" : 6,
					"id" : "SUPPORT_OBJECTS::@eb26578ef4342958058a",
					"jsonFile" : "target-SUPPORT_OBJECTS-Release-920badb61cd04942a524.json",
					"name" : "SUPPORT_OBJECTS",
					"projectIndex" : 0
				},
				{
					"directoryIndex" : 9,
					"id" : "TeapotBasic::@e35cb58959e57316dddd",
					"jsonFile" : "target-TeapotBasic-Release-1567a2bb0b551c1f8c93.json",
					"name" : "TeapotBasic",
					"projectIndex" : 4
				},
				{
					"directoryIndex" : 9,
					"id" : "Triangle::@e35cb58959e57316dddd",
					"jsonFile" : "target-Triangle-Release-f950f54014ee6d7a9b77.json",
					"name" : "Triangle",
					"projectIndex" : 4
				},
				{
					"directoryIndex" : 0,
					"id" : "ZERO_CHECK::@6890427a1f51a3e7e1df",
					"jsonFile" : "target-ZERO_CHECK-Release-251a86dddb8cffc32e6c.json",
					"name" : "ZERO_CHECK",
					"projectIndex" : 0
				},
				{
					"directoryIndex" : 3,
					"id" : "glfw::@82b6fd495907bb2a0cc8",
					"jsonFile" : "target-glfw-Release-d32b7176aa0283165789.json",
					"name" : "glfw",
					"projectIndex" : 1
				},
				{
					"directoryIndex" : 5,
					"id" : "tinyobjloader::@f5b758276623e14bdd9d",
					"jsonFile" : "target-tinyobjloader-Release-c6ddd5e76dc6dec474d1.json",
					"name" : "tinyobjloader",
					"projectIndex" : 2
				},
				{
					"directoryIndex" : 2,
					"id" : "uninstall::@bbdae231e67c99e26acc",
					"jsonFile" : "target-uninstall-Release-5c6bd9945a3443d87f85.json",
					"name" : "uninstall",
					"projectIndex" : 1
				},
				{
					"directoryIndex" : 3,
					"id" : "update_mappings::@82b6fd495907bb2a0cc8",
					"jsonFile" : "target-update_mappings-Release-ff72683483d2b26869b9.json",
					"name" : "update_mappings",
					"projectIndex" : 1
				}
			]
		},
		{
			"directories" : 
			[
				{
					"build" : ".",
					"childIndexes" : 
					[
						1,
						6,
						8
					],
					"hasInstallRule" : true,
					"jsonFile" : "directory-.-MinSizeRel-d0094a50bb2071803777.json",
					"minimumCMakeVersion" : 
					{
						"string" : "3.30"
					},
					"projectIndex" : 0,
					"source" : ".",
					"targetIndexes" : 
					[
						0,
						8,
						12
					]
				},
				{
					"build" : "ExternalProjects",
					"childIndexes" : 
					[
						2,
						5
					],
					"hasInstallRule" : true,
					"jsonFile" : "directory-ExternalProjects-MinSizeRel-922e8866d1c48627fdd8.json",
					"minimumCMakeVersion" : 
					{
						"string" : "3.30"
					},
					"parentIndex" : 0,
					"projectIndex" : 0,
					"source" : "ExternalProjects",
					"targetIndexes" : 
					[
						5
					]
				},
				{
					"build" : "ExternalProjects/glfw",
					"childIndexes" : 
					[
						3,
						4
					],
					"hasInstallRule" : true,
					"jsonFile" : "directory-ExternalProjects.glfw-MinSizeRel-ea1df67d390e019927b6.json",
					"minimumCMakeVersion" : 
					{
						"string" : "3.16"
					},
					"parentIndex" : 1,
					"projectIndex" : 1,
					"source" : "ExternalProjects/glfw",
					"targetIndexes" : 
					[
						1,
						15
					]
				},
				{
					"build" : "ExternalProjects/glfw/src",
					"hasInstallRule" : true,
					"jsonFile" : "directory-ExternalProjects.glfw.src-MinSizeRel-22290071179df8f4cc92.json",
					"minimumCMakeVersion" : 
					{
						"string" : "3.16"
					},
					"parentIndex" : 2,
					"projectIndex" : 1,
					"source" : "ExternalProjects/glfw/src",
					"targetIndexes" : 
					[
						13,
						16
					]
				},
				{
					"build" : "ExternalProjects/glfw/docs",
					"jsonFile" : "directory-ExternalProjects.glfw.docs-MinSizeRel-532e040bf42a7d32092a.json",
					"minimumCMakeVersion" : 
					{
						"string" : "3.16"
					},
					"parentIndex" : 2,
					"projectIndex" : 1,
					"source" : "ExternalProjects/glfw/docs"
				},
				{
					"build" : "ExternalProjects/tinyobjloader",
					"hasInstallRule" : true,
					"jsonFile" : "directory-ExternalProjects.tinyobjloader-MinSizeRel-32435ae2c125da505b07.json",
					"minimumCMakeVersion" : 
					{
						"string" : "3.16"
					},
					"parentIndex" : 1,
					"projectIndex" : 2,
					"source" : "ExternalProjects/tinyobjloader",
					"targetIndexes" : 
					[
						2,
						14
					]
				},
				{
					"build" : "SupportProjects",
					"childIndexes" : 
					[
						7
					],
					"jsonFile" : "directory-SupportProjects-MinSizeRel-4b0124a991b4f3aaa621.json",
					"minimumCMakeVersion" : 
					{
						"string" : "3.30"
					},
					"parentIndex" : 0,
					"projectIndex" : 0,
					"source" : "SupportProjects",
					"targetIndexes" : 
					[
						9
					]
				},
				{
					"build" : "SupportProjects/NeftyRenderTools",
					"jsonFile" : "directory-SupportProjects.NeftyRenderTools-MinSizeRel-a11cc44d347d24b5317d.json",
					"minimumCMakeVersion" : 
					{
						"string" : "3.30"
					},
					"parentIndex" : 6,
					"projectIndex" : 3,
					"source" : "SupportProjects/NeftyRenderTools",
					"targetIndexes" : 
					[
						3,
						6,
						7
					]
				},
				{
					"build" : "MainProject",
					"childIndexes" : 
					[
						9
					],
					"jsonFile" : "directory-MainProject-MinSizeRel-01b36ebcf08f83310bad.json",
					"minimumCMakeVersion" : 
					{
						"string" : "3.30.0"
					},
					"parentIndex" : 0,
					"projectIndex" : 4,
					"source" : "MainProject",
					"targetIndexes" : 
					[
						4
					]
				},
				{
					"build" : "MainProject/Product",
					"jsonFile" : "directory-MainProject.Product-MinSizeRel-6430a5e855460a19d6c4.json",
					"minimumCMakeVersion" : 
					{
						"string" : "3.30.0"
					},
					"parentIndex" : 8,
					"projectIndex" : 4,
					"source" : "MainProject/Product",
					"targetIndexes" : 
					[
						10,
						11
					]
				}
			],
			"name" : "MinSizeRel",
			"projects" : 
			[
				{
					"childIndexes" : 
					[
						1,
						2,
						3,
						4
					],
					"directoryIndexes" : 
					[
						0,
						1,
						6
					],
					"name" : "RayStudioPhase_1",
					"targetIndexes" : 
					[
						0,
						5,
						8,
						9,
						12
					]
				},
				{
					"directoryIndexes" : 
					[
						2,
						3,
						4
					],
					"name" : "GLFW",
					"parentIndex" : 0,
					"targetIndexes" : 
					[
						1,
						13,
						15,
						16
					]
				},
				{
					"directoryIndexes" : 
					[
						5
					],
					"name" : "tinyobjloader",
					"parentIndex" : 0,
					"targetIndexes" : 
					[
						2,
						14
					]
				},
				{
					"directoryIndexes" : 
					[
						7
					],
					"name" : "SupporterNeftyRenderTools",
					"parentIndex" : 0,
					"targetIndexes" : 
					[
						3,
						6,
						7
					]
				},
				{
					"directoryIndexes" : 
					[
						8,
						9
					],
					"name" : "Seohyuk",
					"parentIndex" : 0,
					"targetIndexes" : 
					[
						4,
						10,
						11
					]
				}
			],
			"targets" : 
			[
				{
					"directoryIndex" : 0,
					"id" : "ALL_BUILD::@6890427a1f51a3e7e1df",
					"jsonFile" : "target-ALL_BUILD-MinSizeRel-d2bce6edf4d055655a1d.json",
					"name" : "ALL_BUILD",
					"projectIndex" : 0
				},
				{
					"directoryIndex" : 2,
					"id" : "ALL_BUILD::@bbdae231e67c99e26acc",
					"jsonFile" : "target-ALL_BUILD-MinSizeRel-ff9bfa6a58bd85a00813.json",
					"name" : "ALL_BUILD",
					"projectIndex" : 1
				},
				{
					"directoryIndex" : 5,
					"id" : "ALL_BUILD::@f5b758276623e14bdd9d",
					"jsonFile" : "target-ALL_BUILD-MinSizeRel-0d2c9e557ee6952a99e1.json",
					"name" : "ALL_BUILD",
					"projectIndex" : 2
				},
				{
					"directoryIndex" : 7,
					"id" : "ALL_BUILD::@ce0a2fa435a966c906ac",
					"jsonFile" : "target-ALL_BUILD-MinSizeRel-2b4cc54be70e18fa6d87.json",
					"name" : "ALL_BUILD",
					"projectIndex" : 3
				},
				{
					"directoryIndex" : 8,
					"id" : "ALL_BUILD::@04e0e633e5cbf44b3816",
					"jsonFile" : "target-ALL_BUILD-MinSizeRel-64e0b1cdc76b906d332f.json",
					"name" : "ALL_BUILD",
					"projectIndex" : 4
				},
				{
					"directoryIndex" : 1,
					"id" : "EXTERNAL_OBJECTS::@1687bc44cdbe44ae90e7",
					"jsonFile" : "target-EXTERNAL_OBJECTS-MinSizeRel-183ce34d7669996c6a5d.json",
					"name" : "EXTERNAL_OBJECTS",
					"projectIndex" : 0
				},
				{
					"directoryIndex" : 7,
					"id" : "NeftyRenderTools::@ce0a2fa435a966c906ac",
					"jsonFile" : "target-NeftyRenderTools-MinSizeRel-cf277445e67357b361bf.json",
					"name" : "NeftyRenderTools",
					"projectIndex" : 3
				},
				{
					"directoryIndex" : 7,
					"id" : "NeftyRenderToolsTest::@ce0a2fa435a966c906ac",
					"jsonFile" : "target-NeftyRenderToolsTest-MinSizeRel-3b55a1ac2ef7043ac76c.json",
					"name" : "NeftyRenderToolsTest",
					"projectIndex" : 3
				},
				{
					"directoryIndex" : 0,
					"id" : "SETUPS::@6890427a1f51a3e7e1df",
					"jsonFile" : "target-SETUPS-MinSizeRel-60f6e4d21ed9a32c1a20.json",
					"name" : "SETUPS",
					"projectIndex" : 0
				},
				{
					"directoryIndex" : 6,
					"id" : "SUPPORT_OBJECTS::@eb26578ef4342958058a",
					"jsonFile" : "target-SUPPORT_OBJECTS-MinSizeRel-920badb61cd04942a524.json",
					"name" : "SUPPORT_OBJECTS",
					"projectIndex" : 0
				},
				{
					"directoryIndex" : 9,
					"id" : "TeapotBasic::@e35cb58959e57316dddd",
					"jsonFile" : "target-TeapotBasic-MinSizeRel-d4a95e83599edab97e9e.json",
					"name" : "TeapotBasic",
					"projectIndex" : 4
				},
				{
					"directoryIndex" : 9,
					"id" : "Triangle::@e35cb58959e57316dddd",
					"jsonFile" : "target-Triangle-MinSizeRel-703f6044290b41aa25f5.json",
					"name" : "Triangle",
					"projectIndex" : 4
				},
				{
					"directoryIndex" : 0,
					"id" : "ZERO_CHECK::@6890427a1f51a3e7e1df",
					"jsonFile" : "target-ZERO_CHECK-MinSizeRel-251a86dddb8cffc32e6c.json",
					"name" : "ZERO_CHECK",
					"projectIndex" : 0
				},
				{
					"directoryIndex" : 3,
					"id" : "glfw::@82b6fd495907bb2a0cc8",
					"jsonFile" : "target-glfw-MinSizeRel-4ec5ec1074649e0d8551.json",
					"name" : "glfw",
					"projectIndex" : 1
				},
				{
					"directoryIndex" : 5,
					"id" : "tinyobjloader::@f5b758276623e14bdd9d",
					"jsonFile" : "target-tinyobjloader-MinSizeRel-9643cf9505077370f19e.json",
					"name" : "tinyobjloader",
					"projectIndex" : 2
				},
				{
					"directoryIndex" : 2,
					"id" : "uninstall::@bbdae231e67c99e26acc",
					"jsonFile" : "target-uninstall-MinSizeRel-5c6bd9945a3443d87f85.json",
					"name" : "uninstall",
					"projectIndex" : 1
				},
				{
					"directoryIndex" : 3,
					"id" : "update_mappings::@82b6fd495907bb2a0cc8",
					"jsonFile" : "target-update_mappings-MinSizeRel-ff72683483d2b26869b9.json",
					"name" : "update_mappings",
					"projectIndex" : 1
				}
			]
		},
		{
			"directories" : 
			[
				{
					"build" : ".",
					"childIndexes" : 
					[
						1,
						6,
						8
					],
					"hasInstallRule" : true,
					"jsonFile" : "directory-.-RelWithDebInfo-d0094a50bb2071803777.json",
					"minimumCMakeVersion" : 
					{
						"string" : "3.30"
					},
					"projectIndex" : 0,
					"source" : ".",
					"targetIndexes" : 
					[
						0,
						8,
						12
					]
				},
				{
					"build" : "ExternalProjects",
					"childIndexes" : 
					[
						2,
						5
					],
					"hasInstallRule" : true,
					"jsonFile" : "directory-ExternalProjects-RelWithDebInfo-922e8866d1c48627fdd8.json",
					"minimumCMakeVersion" : 
					{
						"string" : "3.30"
					},
					"parentIndex" : 0,
					"projectIndex" : 0,
					"source" : "ExternalProjects",
					"targetIndexes" : 
					[
						5
					]
				},
				{
					"build" : "ExternalProjects/glfw",
					"childIndexes" : 
					[
						3,
						4
					],
					"hasInstallRule" : true,
					"jsonFile" : "directory-ExternalProjects.glfw-RelWithDebInfo-ea1df67d390e019927b6.json",
					"minimumCMakeVersion" : 
					{
						"string" : "3.16"
					},
					"parentIndex" : 1,
					"projectIndex" : 1,
					"source" : "ExternalProjects/glfw",
					"targetIndexes" : 
					[
						1,
						15
					]
				},
				{
					"build" : "ExternalProjects/glfw/src",
					"hasInstallRule" : true,
					"jsonFile" : "directory-ExternalProjects.glfw.src-RelWithDebInfo-bfd224f4f4c0e9939152.json",
					"minimumCMakeVersion" : 
					{
						"string" : "3.16"
					},
					"parentIndex" : 2,
					"projectIndex" : 1,
					"source" : "ExternalProjects/glfw/src",
					"targetIndexes" : 
					[
						13,
						16
					]
				},
				{
					"build" : "ExternalProjects/glfw/docs",
					"jsonFile" : "directory-ExternalProjects.glfw.docs-RelWithDebInfo-532e040bf42a7d32092a.json",
					"minimumCMakeVersion" : 
					{
						"string" : "3.16"
					},
					"parentIndex" : 2,
					"projectIndex" : 1,
					"source" : "ExternalProjects/glfw/docs"
				},
				{
					"build" : "ExternalProjects/tinyobjloader",
					"hasInstallRule" : true,
					"jsonFile" : "directory-ExternalProjects.tinyobjloader-RelWithDebInfo-e38b497b7bf85bcafb5b.json",
					"minimumCMakeVersion" : 
					{
						"string" : "3.16"
					},
					"parentIndex" : 1,
					"projectIndex" : 2,
					"source" : "ExternalProjects/tinyobjloader",
					"targetIndexes" : 
					[
						2,
						14
					]
				},
				{
					"build" : "SupportProjects",
					"childIndexes" : 
					[
						7
					],
					"jsonFile" : "directory-SupportProjects-RelWithDebInfo-4b0124a991b4f3aaa621.json",
					"minimumCMakeVersion" : 
					{
						"string" : "3.30"
					},
					"parentIndex" : 0,
					"projectIndex" : 0,
					"source" : "SupportProjects",
					"targetIndexes" : 
					[
						9
					]
				},
				{
					"build" : "SupportProjects/NeftyRenderTools",
					"jsonFile" : "directory-SupportProjects.NeftyRenderTools-RelWithDebInfo-a11cc44d347d24b5317d.json",
					"minimumCMakeVersion" : 
					{
						"string" : "3.30"
					},
					"parentIndex" : 6,
					"projectIndex" : 3,
					"source" : "SupportProjects/NeftyRenderTools",
					"targetIndexes" : 
					[
						3,
						6,
						7
					]
				},
				{
					"build" : "MainProject",
					"childIndexes" : 
					[
						9
					],
					"jsonFile" : "directory-MainProject-RelWithDebInfo-01b36ebcf08f83310bad.json",
					"minimumCMakeVersion" : 
					{
						"string" : "3.30.0"
					},
					"parentIndex" : 0,
					"projectIndex" : 4,
					"source" : "MainProject",
					"targetIndexes" : 
					[
						4
					]
				},
				{
					"build" : "MainProject/Product",
					"jsonFile" : "directory-MainProject.Product-RelWithDebInfo-6430a5e855460a19d6c4.json",
					"minimumCMakeVersion" : 
					{
						"string" : "3.30.0"
					},
					"parentIndex" : 8,
					"projectIndex" : 4,
					"source" : "MainProject/Product",
					"targetIndexes" : 
					[
						10,
						11
					]
				}
			],
			"name" : "RelWithDebInfo",
			"projects" : 
			[
				{
					"childIndexes" : 
					[
						1,
						2,
						3,
						4
					],
					"directoryIndexes" : 
					[
						0,
						1,
						6
					],
					"name" : "RayStudioPhase_1",
					"targetIndexes" : 
					[
						0,
						5,
						8,
						9,
						12
					]
				},
				{
					"directoryIndexes" : 
					[
						2,
						3,
						4
					],
					"name" : "GLFW",
					"parentIndex" : 0,
					"targetIndexes" : 
					[
						1,
						13,
						15,
						16
					]
				},
				{
					"directoryIndexes" : 
					[
						5
					],
					"name" : "tinyobjloader",
					"parentIndex" : 0,
					"targetIndexes" : 
					[
						2,
						14
					]
				},
				{
					"directoryIndexes" : 
					[
						7
					],
					"name" : "SupporterNeftyRenderTools",
					"parentIndex" : 0,
					"targetIndexes" : 
					[
						3,
						6,
						7
					]
				},
				{
					"directoryIndexes" : 
					[
						8,
						9
					],
					"name" : "Seohyuk",
					"parentIndex" : 0,
					"targetIndexes" : 
					[
						4,
						10,
						11
					]
				}
			],
			"targets" : 
			[
				{
					"directoryIndex" : 0,
					"id" : "ALL_BUILD::@6890427a1f51a3e7e1df",
					"jsonFile" : "target-ALL_BUILD-RelWithDebInfo-d2bce6edf4d055655a1d.json",
					"name" : "ALL_BUILD",
					"projectIndex" : 0
				},
				{
					"directoryIndex" : 2,
					"id" : "ALL_BUILD::@bbdae231e67c99e26acc",
					"jsonFile" : "target-ALL_BUILD-RelWithDebInfo-ff9bfa6a58bd85a00813.json",
					"name" : "ALL_BUILD",
					"projectIndex" : 1
				},
				{
					"directoryIndex" : 5,
					"id" : "ALL_BUILD::@f5b758276623e14bdd9d",
					"jsonFile" : "target-ALL_BUILD-RelWithDebInfo-0d2c9e557ee6952a99e1.json",
					"name" : "ALL_BUILD",
					"projectIndex" : 2
				},
				{
					"directoryIndex" : 7,
					"id" : "ALL_BUILD::@ce0a2fa435a966c906ac",
					"jsonFile" : "target-ALL_BUILD-RelWithDebInfo-2b4cc54be70e18fa6d87.json",
					"name" : "ALL_BUILD",
					"projectIndex" : 3
				},
				{
					"directoryIndex" : 8,
					"id" : "ALL_BUILD::@04e0e633e5cbf44b3816",
					"jsonFile" : "target-ALL_BUILD-RelWithDebInfo-64e0b1cdc76b906d332f.json",
					"name" : "ALL_BUILD",
					"projectIndex" : 4
				},
				{
					"directoryIndex" : 1,
					"id" : "EXTERNAL_OBJECTS::@1687bc44cdbe44ae90e7",
					"jsonFile" : "target-EXTERNAL_OBJECTS-RelWithDebInfo-183ce34d7669996c6a5d.json",
					"name" : "EXTERNAL_OBJECTS",
					"projectIndex" : 0
				},
				{
					"directoryIndex" : 7,
					"id" : "NeftyRenderTools::@ce0a2fa435a966c906ac",
					"jsonFile" : "target-NeftyRenderTools-RelWithDebInfo-d21b67162e8d71d2975b.json",
					"name" : "NeftyRenderTools",
					"projectIndex" : 3
				},
				{
					"directoryIndex" : 7,
					"id" : "NeftyRenderToolsTest::@ce0a2fa435a966c906ac",
					"jsonFile" : "target-NeftyRenderToolsTest-RelWithDebInfo-f54bdad7a755b7839916.json",
					"name" : "NeftyRenderToolsTest",
					"projectIndex" : 3
				},
				{
					"directoryIndex" : 0,
					"id" : "SETUPS::@6890427a1f51a3e7e1df",
					"jsonFile" : "target-SETUPS-RelWithDebInfo-60f6e4d21ed9a32c1a20.json",
					"name" : "SETUPS",
					"projectIndex" : 0
				},
				{
					"directoryIndex" : 6,
					"id" : "SUPPORT_OBJECTS::@eb26578ef4342958058a",
					"jsonFile" : "target-SUPPORT_OBJECTS-RelWithDebInfo-920badb61cd04942a524.json",
					"name" : "SUPPORT_OBJECTS",
					"projectIndex" : 0
				},
				{
					"directoryIndex" : 9,
					"id" : "TeapotBasic::@e35cb58959e57316dddd",
					"jsonFile" : "target-TeapotBasic-RelWithDebInfo-b3001e8d1c1eacb67cd2.json",
					"name" : "TeapotBasic",
					"projectIndex" : 4
				},
				{
					"directoryIndex" : 9,
					"id" : "Triangle::@e35cb58959e57316dddd",
					"jsonFile" : "target-Triangle-RelWithDebInfo-7d4c5abf8bf7e44d3fb2.json",
					"name" : "Triangle",
					"projectIndex" : 4
				},
				{
					"directoryIndex" : 0,
					"id" : "ZERO_CHECK::@6890427a1f51a3e7e1df",
					"jsonFile" : "target-ZERO_CHECK-RelWithDebInfo-251a86dddb8cffc32e6c.json",
					"name" : "ZERO_CHECK",
					"projectIndex" : 0
				},
				{
					"directoryIndex" : 3,
					"id" : "glfw::@82b6fd495907bb2a0cc8",
					"jsonFile" : "target-glfw-RelWithDebInfo-1688e1559bbe8dd7474e.json",
					"name" : "glfw",
					"projectIndex" : 1
				},
				{
					"directoryIndex" : 5,
					"id" : "tinyobjloader::@f5b758276623e14bdd9d",
					"jsonFile" : "target-tinyobjloader-RelWithDebInfo-8c443ff1367ee9e4ced7.json",
					"name" : "tinyobjloader",
					"projectIndex" : 2
				},
				{
					"directoryIndex" : 2,
					"id" : "uninstall::@bbdae231e67c99e26acc",
					"jsonFile" : "target-uninstall-RelWithDebInfo-5c6bd9945a3443d87f85.json",
					"name" : "uninstall",
					"projectIndex" : 1
				},
				{
					"directoryIndex" : 3,
					"id" : "update_mappings::@82b6fd495907bb2a0cc8",
					"jsonFile" : "target-update_mappings-RelWithDebInfo-ff72683483d2b26869b9.json",
					"name" : "update_mappings",
					"projectIndex" : 1
				}
			]
		}
	],
	"kind" : "codemodel",
	"paths" : 
	{
		"build" : "C:/Users/nefty/workspace/RayStudio2/Seohyuk/cmake-build-debug-visual-studio",
		"source" : "C:/Users/nefty/workspace/RayStudio2/Seohyuk"
	},
	"version" : 
	{
		"major" : 2,
		"minor" : 7
	}
}
